timeseriesmetrics/__init__.py
timeseriesmetrics/metrics.py
timeseriesmetrics-0.2.2.dist-info/LICENSE
timeseriesmetrics-0.2.2.dist-info/METADATA
timeseriesmetrics-0.2.2.dist-info/WHEEL
timeseriesmetrics-0.2.2.dist-info/RECORD
