Metadata-Version: 2.3
Name: timeseriesmetrics
Version: 0.2.2
Summary: This package provides a comprehensive set of metrics designed to evaluate the performance of predictive models for time series. It includes commonly used metrics such as MAPE, Theil's U, ARV, ID (Index of Disagreement), and WPOCID.
License: MIT
Author: danttis
Author-email: juniordante01@gmail.com
Requires-Python: >=3.8
Classifier: Development Status :: 5 - Production/Stable
Classifier: Intended Audience :: Developers
Classifier: Intended Audience :: Science/Research
Classifier: License :: OSI Approved :: MIT License
Classifier: Operating System :: OS Independent
Classifier: Programming Language :: Python :: 3
Classifier: Programming Language :: Python :: 3.8
Classifier: Programming Language :: Python :: 3.9
Classifier: Programming Language :: Python :: 3.10
Classifier: Programming Language :: Python :: 3.11
Classifier: Programming Language :: Python :: 3.12
Classifier: Programming Language :: Python :: 3.13
Classifier: Topic :: Scientific/Engineering
Classifier: Topic :: Software Development
Requires-Dist: numpy (>=2.1.1)
Requires-Dist: pandas (>=2.0.0)
